<?xml version="1.0" encoding="utf-8"?>
<SetData>
  <Object type="townsman" id="0">
    <CustomData />
    <Parameters>
      <Parameter type="String"></Parameter>
      <Parameter type="Int32">14</Parameter>
      <Parameter type="Int32">0</Parameter>
      <Parameter type="Int32">0</Parameter>
      <Parameter type="String"></Parameter>
      <Parameter type="String"></Parameter>
      <Parameter type="String"></Parameter>
      <Parameter type="String">msg_m1005_005</Parameter>
      <Parameter type="Vector3">
        <x>0</x>
        <y>0</y>
        <z>0</z>
      </Parameter>
      <Parameter type="UInt32">4294967295</Parameter>
      <Parameter type="Int32">2</Parameter>
      <Parameter type="Int32">1</Parameter>
      <Parameter type="String"></Parameter>
      <Parameter type="String"></Parameter>
      <Parameter type="Boolean">False</Parameter>
      <Parameter type="Boolean">False</Parameter>
      <Parameter type="UInt32">4294967295</Parameter>
      <Parameter type="Int32">0</Parameter>
    </Parameters>
    <Transforms>
      <Transform>
        <Position>
          <x>22610.6</x>
          <y>200.124</y>
          <z>-127.47</z>
        </Position>
        <Rotation>
          <x>0</x>
          <y>-0.258819</y>
          <z>0</z>
          <w>0.965926</w>
        </Rotation>
        <Scale>
          <x>1</x>
          <y>1</y>
          <z>1</z>
        </Scale>
      </Transform>
    </Transforms>
  </Object>
  <Object type="townsman" id="0">
    <CustomData />
    <Parameters>
      <Parameter type="String"></Parameter>
      <Parameter type="Int32">14</Parameter>
      <Parameter type="Int32">0</Parameter>
      <Parameter type="Int32">0</Parameter>
      <Parameter type="String"></Parameter>
      <Parameter type="String"></Parameter>
      <Parameter type="String">wait_arm</Parameter>
      <Parameter type="String"></Parameter>
      <Parameter type="Vector3">
        <x>0</x>
        <y>0</y>
        <z>0</z>
      </Parameter>
      <Parameter type="UInt32">4294967295</Parameter>
      <Parameter type="Int32">1</Parameter>
      <Parameter type="Int32">1</Parameter>
      <Parameter type="String"></Parameter>
      <Parameter type="String"></Parameter>
      <Parameter type="Boolean">False</Parameter>
      <Parameter type="Boolean">False</Parameter>
      <Parameter type="UInt32">4294967295</Parameter>
      <Parameter type="Int32">0</Parameter>
    </Parameters>
    <Transforms>
      <Transform>
        <Position>
          <x>22455.5</x>
          <y>200</y>
          <z>-325.734</z>
        </Position>
        <Rotation>
          <x>0</x>
          <y>0.173648</y>
          <z>0</z>
          <w>0.984808</w>
        </Rotation>
        <Scale>
          <x>1</x>
          <y>1</y>
          <z>1</z>
        </Scale>
      </Transform>
    </Transforms>
  </Object>
  <Object type="townsman" id="0">
    <CustomData />
    <Parameters>
      <Parameter type="String"></Parameter>
      <Parameter type="Int32">14</Parameter>
      <Parameter type="Int32">0</Parameter>
      <Parameter type="Int32">0</Parameter>
      <Parameter type="String"></Parameter>
      <Parameter type="String"></Parameter>
      <Parameter type="String">wave_bothhands</Parameter>
      <Parameter type="String"></Parameter>
      <Parameter type="Vector3">
        <x>0</x>
        <y>0</y>
        <z>0</z>
      </Parameter>
      <Parameter type="UInt32">4294967295</Parameter>
      <Parameter type="Int32">2</Parameter>
      <Parameter type="Int32">1</Parameter>
      <Parameter type="String"></Parameter>
      <Parameter type="String"></Parameter>
      <Parameter type="Boolean">False</Parameter>
      <Parameter type="Boolean">False</Parameter>
      <Parameter type="UInt32">4294967295</Parameter>
      <Parameter type="Int32">0</Parameter>
    </Parameters>
    <Transforms>
      <Transform>
        <Position>
          <x>22803.3</x>
          <y>200.124</y>
          <z>-149.583</z>
        </Position>
        <Rotation>
          <x>0</x>
          <y>-0.300706</y>
          <z>0</z>
          <w>0.953717</w>
        </Rotation>
        <Scale>
          <x>1</x>
          <y>1</y>
          <z>1</z>
        </Scale>
      </Transform>
    </Transforms>
  </Object>
  <Object type="townsman" id="0">
    <CustomData />
    <Parameters>
      <Parameter type="String"></Parameter>
      <Parameter type="Int32">14</Parameter>
      <Parameter type="Int32">0</Parameter>
      <Parameter type="Int32">0</Parameter>
      <Parameter type="String"></Parameter>
      <Parameter type="String"></Parameter>
      <Parameter type="String"></Parameter>
      <Parameter type="String"></Parameter>
      <Parameter type="Vector3">
        <x>0</x>
        <y>0</y>
        <z>0</z>
      </Parameter>
      <Parameter type="UInt32">4294967295</Parameter>
      <Parameter type="Int32">1</Parameter>
      <Parameter type="Int32">1</Parameter>
      <Parameter type="String"></Parameter>
      <Parameter type="String"></Parameter>
      <Parameter type="Boolean">False</Parameter>
      <Parameter type="Boolean">False</Parameter>
      <Parameter type="UInt32">4294967295</Parameter>
      <Parameter type="Int32">0</Parameter>
    </Parameters>
    <Transforms>
      <Transform>
        <Position>
          <x>22685</x>
          <y>200.124</y>
          <z>-286.871</z>
        </Position>
        <Rotation>
          <x>0</x>
          <y>-0.21644</y>
          <z>0</z>
          <w>0.976296</w>
        </Rotation>
        <Scale>
          <x>1</x>
          <y>1</y>
          <z>1</z>
        </Scale>
      </Transform>
    </Transforms>
  </Object>
  <Object type="player_start2" id="0">
    <CustomData />
    <Parameters>
      <Parameter type="Int32">0</Parameter>
      <Parameter type="String">sonic_new</Parameter>
      <Parameter type="Boolean">False</Parameter>
    </Parameters>
    <Transforms>
      <Transform>
        <Position>
          <x>22560.1</x>
          <y>199.99</y>
          <z>-56.4308</z>
        </Position>
        <Rotation>
          <x>-0</x>
          <y>0.965926</y>
          <z>-0</z>
          <w>0.258819</w>
        </Rotation>
        <Scale>
          <x>1</x>
          <y>1</y>
          <z>1</z>
        </Scale>
      </Transform>
    </Transforms>
  </Object>
  <Object type="townsman" id="0">
    <CustomData />
    <Parameters>
      <Parameter type="String"></Parameter>
      <Parameter type="Int32">33</Parameter>
      <Parameter type="Int32">0</Parameter>
      <Parameter type="Int32">0</Parameter>
      <Parameter type="String"></Parameter>
      <Parameter type="String"></Parameter>
      <Parameter type="String"></Parameter>
      <Parameter type="String"></Parameter>
      <Parameter type="Vector3">
        <x>0</x>
        <y>0</y>
        <z>0</z>
      </Parameter>
      <Parameter type="UInt32">4294967295</Parameter>
      <Parameter type="Int32">2</Parameter>
      <Parameter type="Int32">1</Parameter>
      <Parameter type="String"></Parameter>
      <Parameter type="String"></Parameter>
      <Parameter type="Boolean">False</Parameter>
      <Parameter type="Boolean">False</Parameter>
      <Parameter type="UInt32">4294967295</Parameter>
      <Parameter type="Int32">0</Parameter>
    </Parameters>
    <Transforms>
      <Transform>
        <Position>
          <x>22737.6</x>
          <y>200</y>
          <z>-20.8564</z>
        </Position>
        <Rotation>
          <x>0</x>
          <y>-0.5373</y>
          <z>-0</z>
          <w>0.843391</w>
        </Rotation>
        <Scale>
          <x>1</x>
          <y>1</y>
          <z>1</z>
        </Scale>
      </Transform>
    </Transforms>
  </Object>
  <Object type="townsman" id="0">
    <CustomData />
    <Parameters>
      <Parameter type="String"></Parameter>
      <Parameter type="Int32">14</Parameter>
      <Parameter type="Int32">0</Parameter>
      <Parameter type="Int32">0</Parameter>
      <Parameter type="String"></Parameter>
      <Parameter type="String"></Parameter>
      <Parameter type="String"></Parameter>
      <Parameter type="String"></Parameter>
      <Parameter type="Vector3">
        <x>0</x>
        <y>0</y>
        <z>0</z>
      </Parameter>
      <Parameter type="UInt32">4294967295</Parameter>
      <Parameter type="Int32">0</Parameter>
      <Parameter type="Int32">1</Parameter>
      <Parameter type="String"></Parameter>
      <Parameter type="String"></Parameter>
      <Parameter type="Boolean">False</Parameter>
      <Parameter type="Boolean">False</Parameter>
      <Parameter type="UInt32">4294967295</Parameter>
      <Parameter type="Int32">0</Parameter>
    </Parameters>
    <Transforms>
      <Transform>
        <Position>
          <x>22424.2</x>
          <y>200</y>
          <z>-163.936</z>
        </Position>
        <Rotation>
          <x>0</x>
          <y>0.21644</y>
          <z>0</z>
          <w>0.976296</w>
        </Rotation>
        <Scale>
          <x>1</x>
          <y>1</y>
          <z>1</z>
        </Scale>
      </Transform>
    </Transforms>
  </Object>
  <Object type="player_goal" id="0">
    <CustomData />
    <Parameters>
      <Parameter type="Vector3">
        <x>22504.8</x>
        <y>250</y>
        <z>641.566</z>
      </Parameter>
      <Parameter type="Vector3">
        <x>22673.6</x>
        <y>250</y>
        <z>578.736</z>
      </Parameter>
    </Parameters>
    <Transforms>
      <Transform>
        <Position>
          <x>22678.9</x>
          <y>199.988</y>
          <z>578.138</z>
        </Position>
        <Rotation>
          <x>0</x>
          <y>-0.173648</y>
          <z>-0</z>
          <w>0.984808</w>
        </Rotation>
        <Scale>
          <x>1</x>
          <y>1</y>
          <z>1</z>
        </Scale>
      </Transform>
    </Transforms>
  </Object>
</SetData>